odoo/addons/pydantic/README.rst
odoo/addons/pydantic/__init__.py
odoo/addons/pydantic/__manifest__.py
odoo/addons/pydantic/utils.py
odoo/addons/pydantic/i18n/it.po
odoo/addons/pydantic/i18n/pydantic.pot
odoo/addons/pydantic/readme/CONTRIBUTORS.md
odoo/addons/pydantic/readme/DESCRIPTION.md
odoo/addons/pydantic/readme/ROADMAP.md
odoo/addons/pydantic/readme/USAGE.md
odoo/addons/pydantic/static/description/icon.png
odoo/addons/pydantic/static/description/index.html
odoo/addons/pydantic/tests/__init__.py
odoo/addons/pydantic/tests/test_pydantic_generic_odoo_getter.py
odoo_addon_pydantic-18.0.1.1.0.dist-info/METADATA
odoo_addon_pydantic-18.0.1.1.0.dist-info/WHEEL
odoo_addon_pydantic-18.0.1.1.0.dist-info/top_level.txt
odoo_addon_pydantic-18.0.1.1.0.dist-info/RECORD
