Metadata-Version: 2.1
Name: odoo-addon-pydantic
Version: 18.0.1.1.0
Requires-Python: >=3.10
Requires-Dist: contextvars
Requires-Dist: odoo==18.0.*
Requires-Dist: pydantic>=2.0.0
Requires-Dist: typing-extensions
Summary: Utility addon to ease mapping between Pydantic and Odoo models
Home-page: https://github.com/OCA/rest-framework
License: LGPL-3
Author: ACSONE SA/NV,Odoo Community Association (OCA)
Author-email: support@odoo-community.org
Classifier: Programming Language :: Python
Classifier: Framework :: Odoo
Classifier: Framework :: Odoo :: 18.0
Classifier: License :: OSI Approved :: GNU Lesser General Public License v3 (LGPLv3)
Classifier: Development Status :: 4 - Beta
